gongy/__init__.py
gongy/api.py
gongy/errors.py
gongy/models.py
gongy/py.typed
gongy/utils/__init__.py
gongy/utils/model_utils.py
gongy/utils/types.py
gongy/utils/web.py
gongy-0.5.3.dist-info/METADATA
gongy-0.5.3.dist-info/WHEEL
gongy-0.5.3.dist-info/licenses/LICENSE
gongy-0.5.3.dist-info/RECORD
