Metadata-Version: 2.4
Name: gongy
Version: 0.5.3
Summary: Unofficial Gong Python SDK.
Project-URL: homepage, https://github.com/MicaelJarniac/gongy
Project-URL: source, https://github.com/MicaelJarniac/gongy
Project-URL: download, https://pypi.org/project/gongy/#files
Project-URL: changelog, https://github.com/MicaelJarniac/gongy/blob/main/docs/CHANGELOG.md
Project-URL: documentation, https://gongy.readthedocs.io
Project-URL: issues, https://github.com/MicaelJarniac/gongy/issues
Author-email: Micael Jarniac <micael@jarniac.dev>
License: MIT
License-File: LICENSE
Classifier: Development Status :: 1 - Planning
Classifier: License :: OSI Approved :: MIT License
Classifier: Natural Language :: English
Classifier: Operating System :: OS Independent
Classifier: Programming Language :: Python :: 3
Classifier: Typing :: Typed
Requires-Python: >=3.13
Requires-Dist: aiohttp>=3.12.15
Requires-Dist: loguru>=0.7.3
Requires-Dist: pydantic[email]>=2.11.7
Requires-Dist: yarl>=1.20.1
